vivraw/__init__.py
vivraw/raw.py
vivraw/test/__init__.py
vivraw/test/test_raw.py
vivraw-0.0.1.dist-info/METADATA
vivraw-0.0.1.dist-info/WHEEL
vivraw-0.0.1.dist-info/top_level.txt
vivraw-0.0.1.dist-info/RECORD
